bugrobot/__init__.py
bugrobot/bugrobot.py
bugrobot-0.4.dist-info/METADATA
bugrobot-0.4.dist-info/WHEEL
bugrobot-0.4.dist-info/top_level.txt
bugrobot-0.4.dist-info/RECORD
