Metadata-Version: 2.1
Name: bugrobot
Version: 0.4
Summary: A useful tool to monitor your running code bug by sending email or wechat message
Home-page: https://github.com/lyhue1991/bugrobot
Author: PythonAiRoad
Author-email: lyhue1991@163.com
License: UNKNOWN
Platform: UNKNOWN
Classifier: Programming Language :: Python :: 3
Classifier: License :: OSI Approved :: MIT License
Classifier: Operating System :: OS Independent
Requires-Python: >=3.5
